{"tripDistance":28144,"originPoint":{"lat":39.766454,"lng":-104.94256200000001},"originSearchRadius":1981.58,"originAddress":{"formatted":"3540 Jackson St, Denver, CO 80205, USA","streetNumber":3540,"streetName":"Jackson St","city":"Denver","state":"CO","zip":80205},"destinationPoint":{"lat":39.727524,"lng":-105.15262899999999},"destinationSearchRadius":9775,"destinationAddress":{"formatted":"13695 W 7th Ave, Golden, CO 80401, USA","streetNumber":13695,"streetName":"W 7th Ave","city":"Golden","state":"CO","zip":80401},"encodedPolyline":"i{uqFzso_SyAA?oB@eG?cA?a@kB?}F?aBAgZCqC@cJLmQ?{HEa@c@ISGWA[BUHUV]JGRAT@TNLRH\\JbABH@n@C|LAfLCp\\EhSAhBFvFC|Z?tKCbGFbNAhL?pAHjKZnOX`KNxHNrGBjGCnEYlJQ|FAzS?`AEhDUfFCn@UvCOjBUrB{@lGyCpP}@hEuAvHO~@c@bCu@|DwAfHeAbGWzBGnAApAFhBl@pITrD@|AIlCy@rTGrIKvR?nBC~QAnCGpAa@rEm@|FUrCGtAG~D@vABbCJtDVfF`@tFzAfQNdCB~BK~EATKrEGpDAhJ?rM?|KCvCCbAMnA[nBo@pBkAxCqAvDUjAOxAMbCBvC`@pDLl@p@~BjCrGl@rBLn@VfCFdB@fF@zI@d_@?rA_@rVIpBOfBo@xD]zAYbAy@|BcAzB{@tAmExFiAdBo@pAg@dB]pBOjBEfBHxBL~Ah@vE|ClSRlA|A|KbB|L~@~FpAlIz@dGZfEHtC@~@F`KBjL@da@GpF]`Hs@rLOxDCfID|d@Dpj@HfERpFd@rGl@tF|@xFh@rCtA|FfKf`@lGvUfA|Dt@vBb@bAl@dAjAfBjAlApAfAbB|@tAf@pAZ`ANrAHdKAzVG~m@QtBBjCH|DXdDb@hEz@v@R~DlAdBp@pB|@pCxAz@f@zE`DnPnLdWrQ|ChCrBrBnBvBvCzDbJzL~^fg@hPrTjGnIlA`BtBtCJh@v@rBrAzERj@l@nAXLH@V?\\Jm@_EQeAuAmJk@kEm@mEc@iDBc@@MDKh@c@bE?pD?vE@fA@tDC?oL?uTCm@EWYk@^w@DUByNC{V","containmentPolygon":[{"lat":39.78728,"lng":-104.93953},{"lat":39.72730000000001,"lng":-104.93953},{"lat":39.72730000000001,"lng":-105.17210000000001},{"lat":39.78728,"lng":-105.17210000000001}],"when":null,"rideOrDrive":"DRIVE","accountId":"e805e86e-f0c2-4c81-8d82-7dfd6a15ef53","id":"13ecc7d0-e71f-4578-aa5c-cbdf00242f02"}